minny/__init__.py
minny/__main__.py
minny/adapters.py
minny/bare_metal.py
minny/circup.py
minny/common.py
minny/compiling.py
minny/connection.py
minny/global-pip-overrides.txt
minny/installer.py
minny/mip.py
minny/parser.py
minny/pip.py
minny/project.py
minny/pyproject_analyzer.py
minny/serial_connection.py
minny/settings.py
minny/tracking.py
minny/util.py
minny/webrepl_connection.py
minny-0.0.1a2.dist-info/WHEEL
minny-0.0.1a2.dist-info/METADATA
minny-0.0.1a2.dist-info/RECORD
