Metadata-Version: 2.4
Name: minny
Version: 0.0.1a2
Summary: Package and project manager for MicroPython and CircuitPython
Keywords: MicroPython,CircuitPython
Author: Aivar Annamaa
Author-email: Aivar Annamaa <aivarannamaa@users.noreply.github.com>
License-Expression: MIT
Classifier: Development Status :: 4 - Beta
Classifier: Programming Language :: Python
Requires-Dist: packaging
Requires-Dist: pyserial
Requires-Dist: filelock
Requires-Dist: websockets
Requires-Dist: mpy-cross-v6-3
Requires-Python: >=3.11
Project-URL: Changelog, https://github.com/aivarannamaa/minny/blob/main/CHANGELOG.md
Project-URL: Documentation, https://github.com/aivarannamaa/minny/blob/main/README.md
Project-URL: Issues, https://github.com/aivarannamaa/minny/issues
Project-URL: Source, https://github.com/aivarannamaa/minny
